papatool/__init__.py
papatool/papatool.py
papatool-0.1.0.dist-info/LICENSE
papatool-0.1.0.dist-info/METADATA
papatool-0.1.0.dist-info/WHEEL
papatool-0.1.0.dist-info/entry_points.txt
papatool-0.1.0.dist-info/top_level.txt
papatool-0.1.0.dist-info/RECORD
