Metadata-Version: 2.1
Name: papatool
Version: 0.1.0
Summary: A package tool for managing Python packages
Home-page: https://github.com/wasit7/package-tool
Author: Wasit Limprasert
Author-email: wasit7@gmail.com
Classifier: Programming Language :: Python :: 3
Classifier: License :: OSI Approved :: MIT License
Classifier: Operating System :: OS Independent
Requires-Python: >=3.6
License-File: LICENSE
Requires-Dist: setuptools
Requires-Dist: wheel
Requires-Dist: twine
